LICENSE
MANIFEST.in
README.rst
VERSION
setup.cfg
setup.py
flowdas.service.egg-info/PKG-INFO
flowdas.service.egg-info/SOURCES.txt
flowdas.service.egg-info/dependency_links.txt
flowdas.service.egg-info/entry_points.txt
flowdas.service.egg-info/not-zip-safe
flowdas.service.egg-info/requires.txt
flowdas.service.egg-info/top_level.txt
flowdas/service/__init__.py
flowdas/service/_config.py
flowdas/service/_console.py
flowdas/service/_errors.py
flowdas/service/_http.py
flowdas/service/_injector.py
flowdas/service/_jsonrpc.py
flowdas/service/_main.py
flowdas/service/_openrpc.py