Metadata-Version: 2.1
Name: flowdas.service
Version: 0.5.1
Summary: Flowdas Service: The OpenRPC Framework
Home-page: https://github.com/flowdas/flowdas.service
Author: Flowdas Inc.
Author-email: propsero@flowdas.com
License: MPL 2.0
Project-URL: Code, https://github.com/flowdas/flowdas.service
Project-URL: Issue tracker, https://github.com/flowdas/flowdas.service/issues
Platform: UNKNOWN
Classifier: Development Status :: 5 - Production/Stable
Classifier: Intended Audience :: Developers
Classifier: License :: OSI Approved :: Mozilla Public License 2.0 (MPL 2.0)
Classifier: Operating System :: OS Independent
Classifier: Programming Language :: Python
Classifier: Programming Language :: Python :: 3
Classifier: Programming Language :: Python :: 3.7
Classifier: Programming Language :: Python :: 3.8
Classifier: Programming Language :: Python :: 3.9
Requires-Python: >=3.7
Provides-Extra: dev
